src/__init__.py
src/conf/config_schema.yaml
src/conf/default.yaml
src/main.py
src/utils.py
forticlean-1.0.0.dist-info/METADATA
forticlean-1.0.0.dist-info/WHEEL
forticlean-1.0.0.dist-info/entry_points.txt
forticlean-1.0.0.dist-info/RECORD
