Metadata-Version: 2.1
Name: forticlean
Version: 1.0.0
Summary: Clean & sort FortiOS config files.
Home-page: https://github.com/ryanmerolle/forticlean
Keywords: fortios,python
Author: Ryan Merolle
Requires-Python: >=3.9,<4.0
Classifier: Intended Audience :: Developers
Classifier: Programming Language :: Python :: 3
Classifier: Programming Language :: Python :: 3.9
Classifier: Programming Language :: Python :: 3.10
Classifier: Programming Language :: Python :: 3.11
Requires-Dist: jsonschema
Requires-Dist: pyyaml
Requires-Dist: rich
Requires-Dist: typer[all]
Project-URL: Documentation, https://github.com/ryanmerolle/forticlean
